paddles
